{
  "dataList": [
    {
      "id": 0,
      "characterlist": "산초:5",
      "feeling": "angry",
      "bg": "story_fathoms_maze_boss03_1",
      "soundeffect": "SFX_Jean_Crumble_Light",
      "voice": "S703V-1211"
    },
    {
      "id": 1,
      "feeling": "sad4",
      "voice": "S703V-1212"
    },
    {
      "id": 2,
      "feeling": "sad5",
      "soundeffect": "SFX_Cotton_Crumble_SoftNew",
      "voice": "S703V-1213"
    },
    {
      "id": 3,
      "feeling": "sad3",
      "soundeffect": "SFX_Cloth_Crumble",
      "voice": "S703V-1214"
    },
    {
      "id": 4,
      "characterlist": "ALL:-1",
      "cg": "S723:FadeIn:[0~1]",
      "effect": "CameraMoveZoom:mode=on:duration=2:vertical=-0.08:zoom=0.85:delay=0",
      "soundeffect": "SFX_Cotton_Crumble_SoftNew",
      "voice": "S703V-1215"
    },
    {
      "id": 5,
      "soundeffect": "SFX_Cloth_Rubbed_Move",
      "voice": "S703V-1216"
    },
    {
      "id": 6,
      "voice": "S703V-1217"
    },
    {
      "id": 7,
      "soundeffect": "SFX_Leather_Crumble_Light",
      "voice": "S703V-1218"
    },
    {
      "id": 8,
      "soundeffect": "SFX_Cotton_Crumble_SoftNew",
      "voice": "S703V-1219"
    },
    {
      "id": 9,
      "voice": "S703V-1220"
    },
    {
      "id": 10,
      "soundeffect": "SFX_Cloth_Crumble",
      "voice": "S703V-1221"
    },
    {
      "id": 11,
      "soundeffect": "SFX_Cotton_Crumble_SoftNew",
      "voice": "S703V-1222"
    },
    {
      "id": 12,
      "soundeffect": "SFX_Jean_Crumble_Light",
      "voice": "S703V-1223"
    },
    {
      "id": 13,
      "soundeffect": "SFX_Cloth_Rubbed_Move",
      "voice": "S703V-1224"
    },
    {
      "id": 14,
      "voice": "S703V-1225"
    },
    {
      "id": 15,
      "soundeffect": "SFX_Walk_Iron_Once",
      "voice": "S703V-1226"
    },
    {
      "id": 16,
      "characterlist": "산초:5",
      "feeling": "close",
      "cg": "S723:FadeOut:[0~1]",
      "effect": "CameraMoveZoom:mode=on:duration=1:delay=0",
      "voice": "S703V-1227"
    },
    {
      "id": 17,
      "feeling": "sad2",
      "soundeffect": "SFX_Cotton_Crumble_SoftNew",
      "voice": "S703V-1228"
    },
    {
      "id": 18,
      "characterlist": "ALL:-1,키호테:3,옛산초:7",
      "feeling": "happy",
      "bg": "story_sheepranch",
      "cg": "black:FadeIn:[0~0.1], black:FadeOut:[0.1~0.2]",
      "soundeffect": "SFX_Cotton_Crumble_Light",
      "voice": "S703V-1229"
    },
    {
      "id": 19,
      "feeling": "smile2",
      "voice": "S703V-1230"
    },
    {
      "id": 20,
      "feeling": "idle",
      "soundeffect": "SFX_Cloth_Crumble",
      "voice": "S703V-1231"
    },
    {
      "id": 21,
      "feeling": "smile2",
      "soundeffect": "SFX_Jean_Crumble_Light",
      "voice": "S703V-1232"
    },
    {
      "id": 22,
      "feeling": "smile",
      "voice": "S703V-1233"
    },
    {
      "id": 23,
      "feeling": "happy",
      "soundeffect": "SFX_Sweat_Crumble_Light",
      "voice": "S703V-1234"
    },
    {
      "id": 24,
      "feeling": "sigh",
      "soundeffect": "SFX_Cloth_Crumble",
      "voice": "S703V-1235"
    },
    {
      "id": 25,
      "feeling": "idle2",
      "soundeffect": "SFX_Cotton_Crumble_SoftNew",
      "voice": "S703V-1236"
    },
    {
      "id": 26,
      "characterlist": "ALL:-1,로시난테:5",
      "voice": "S703V-1237"
    },
    {
      "id": 27,
      "characterlist": "ALL:-1,키호테:3,옛산초:7",
      "feeling": "shork",
      "soundeffect": "SFX_Jean_Crumble_Light",
      "voice": "S703V-1238"
    },
    {
      "id": 28,
      "feeling": "angry",
      "soundeffect": "SFX_Cotton_Crumble_SoftNew",
      "voice": "S703V-1239"
    },
    {
      "id": 29,
      "feeling": "smile3",
      "soundeffect": "SFX_Cloth_Crumble",
      "voice": "S703V-1240"
    },
    {
      "id": 30,
      "feeling": "close",
      "soundeffect": "SFX_Leather_Crumble_Light",
      "voice": "S703V-1241"
    },
    {
      "id": 31,
      "feeling": "surprise",
      "soundeffect": "SFX_Hair_Care_2",
      "voice": "S703V-1242"
    },
    {
      "id": 32,
      "feeling": "smile",
      "voice": "S703V-1243"
    },
    {
      "id": 33,
      "feeling": "smile2",
      "soundeffect": "SFX_Cotton_Crumble_SoftNew",
      "voice": "S703V-1244"
    },
    {
      "id": 34,
      "feeling": "surprise",
      "voice": "S703V-1245"
    },
    {
      "id": 35,
      "feeling": "idle",
      "soundeffect": "SFX_Cloth_Crumble",
      "voice": "S703V-1246"
    },
    {
      "id": 36,
      "feeling": "wink",
      "soundeffect": "SFX_Leather_Crumble_Light",
      "voice": "S703V-1247"
    },
    {
      "id": 37,
      "cg": "black:FadeIn",
      "voice": "S703V-1248",
      "monologue": true
    },
    {
      "id": 38,
      "characterlist": "ALL:-1,키호테:3,옛산초:7",
      "cg": "black:FadeOut",
      "soundeffect": "SFX_Cotton_Crumble_SoftNew",
      "voice": "S703V-1249"
    },
    {
      "id": 39,
      "soundeffect": "SFX_Jean_Crumble_Light",
      "voice": "S703V-1250"
    },
    {
      "id": 40,
      "soundeffect": "SFX_Cloth_Crumble",
      "voice": "S703V-1251"
    },
    {
      "id": 41,
      "characterlist": "ALL:-1",
      "feeling": "smile2",
      "cg": "black:FadeIn",
      "voice": "S703V-1252",
      "monologue": true
    },
    {
      "id": 42,
      "characterlist": "키호테:5",
      "feeling": "smile",
      "bg": "story_donquixote_mansion",
      "cg": "black:FadeOut",
      "soundeffect": "SFX_Walk_Iron_Once",
      "voice": "S703V-1253"
    },
    {
      "id": 43,
      "feeling": "smile",
      "soundeffect": "SFX_Walk_Wood_2StepOnly",
      "voice": "S703V-1254"
    },
    {
      "id": 44,
      "feeling": "smile2",
      "soundeffect": "SFX_Walk_Stone",
      "voice": "S703V-1255"
    },
    {
      "id": 45,
      "feeling": "smile2",
      "voice": "S703V-1256"
    },
    {
      "id": 46,
      "feeling": "happy",
      "voice": "S703V-1257"
    },
    {
      "id": 47,
      "feeling": "happy",
      "soundeffect": "SFX_Cotton_Crumble_SoftNew",
      "voice": "S703V-1258"
    },
    {
      "id": 48,
      "feeling": "smile3",
      "soundeffect": "SFX_Jean_Crumble_Light",
      "voice": "S703V-1259"
    },
    {
      "id": 49,
      "characterlist": "바리:5",
      "voice": "S703V-1260"
    },
    {
      "id": 50,
      "feeling": "smile",
      "soundeffect": "SFX_Cotton_Crumble_SoftNew, SFX_MetalCrumble",
      "voice": "S703V-1261"
    },
    {
      "id": 51,
      "voice": "S703V-1262"
    },
    {
      "id": 52,
      "soundeffect": "SFX_Jean_Crumble_Light",
      "voice": "S703V-1263"
    },
    {
      "id": 53,
      "feeling": "smile",
      "soundeffect": "SFX_Metalarm",
      "voice": "S703V-1264"
    },
    {
      "id": 54,
      "characterlist": "ALL:-1,키호테:3,산초:7",
      "feeling": "smile",
      "soundeffect": "SFX_Leather_Crumble_Light",
      "voice": "S703V-1265"
    },
    {
      "id": 55,
      "characterlist": "ALL:-1,바리:5",
      "feeling": "smile",
      "soundeffect": "SFX_Cotton_Crumble_SoftNew, SFX_MetalCrumble",
      "voice": "S703V-1269"
    },
    {
      "id": 56,
      "feeling": "smile",
      "soundeffect": "SFX_Walk_Dirt",
      "voice": "S703V-1270"
    },
    {
      "id": 57,
      "characterlist": "ALL:-1,산초:5",
      "feeling": "sad2",
      "bg": "story_fathoms_maze_boss03_1",
      "cg": "black:FadeOut",
      "voice": "S703V-1271"
    },
    {
      "id": 58,
      "feeling": "sad3",
      "voice": "S703V-1272"
    },
    {
      "id": 59,
      "characterlist": "키호테빛:5:mode=FADE_IN",
      "feeling": "old4",
      "voice": "S703V-1273"
    }
  ]
}