{
  "dataList": [
    {
      "id": 0,
      "characterlist": "죄수 : -1 : mode=FADE_OUT",
      "bg": "story_fathoms_lab_b",
      "effect": "CustomCamShake:[10][10][0.5]",
      "bgm": "Brutality",
      "soundeffect": "SFX_Small_Metal_Clank"
    },
    {
      "id": 1,
      "effect": "CustomCamShake:[8][7][1]",
      "soundeffect": "MicNoise",
      "voice": "S802V-624"
    },
    {
      "id": 2,
      "voice": "S802V-625"
    },
    {
      "id": 3,
      "voice": "S802V-626"
    },
    {
      "id": 4
    },
    {
      "id": 5,
      "characterlist": "이상 : 3, 홍루 : 8",
      "feeling": "shock",
      "soundeffect": "SFX_Walk_Iron_Once",
      "voice": "S802V-628"
    },
    {
      "id": 6,
      "soundeffect": "SFX_Cotton_Crumble_SoftNew",
      "voice": "S802V-629"
    },
    {
      "id": 7,
      "feeling": "close",
      "voice": "S802V-630"
    },
    {
      "id": 8,
      "feeling": "sad",
      "soundeffect": "SFX_Cloth_Crumble",
      "voice": "S802V-631"
    },
    {
      "id": 9,
      "feeling": "angry",
      "voice": "S802V-632"
    },
    {
      "id": 10,
      "feeling": "idle",
      "soundeffect": "SFX_Cotton_Crumble_SoftNew",
      "voice": "S802V-633"
    },
    {
      "id": 11,
      "characterlist": "ALL:-1,오티스 : 2",
      "feeling": "panic2",
      "soundeffect": "SFX_Walk_Wood_2StepOnly",
      "voice": "S802V-634"
    },
    {
      "id": 12,
      "feeling": "idle",
      "soundeffect": "SFX_Jean_Crumble_Light",
      "voice": "S802V-635"
    },
    {
      "id": 13,
      "characterlist": "임대옥 : 9",
      "feeling": "idle3",
      "soundeffect": "SFX_Cloth_Crumble",
      "voice": "S802V-636"
    },
    {
      "id": 14,
      "feeling": "idle",
      "voice": "S802V-637"
    },
    {
      "id": 15,
      "characterlist": "홍루:5",
      "voice": "S802V-638"
    },
    {
      "id": 16,
      "characterlist": "ALL : -1, 어린임대옥 : 2",
      "feeling": "angry",
      "bg": "story_outside the dungeon_past",
      "cg": "white:FadeIn:[0~0.1],white:FadeOut:[0.1~0.2]",
      "bgm": "Remembrance-1",
      "soundeffect": "SFX_Cotton_Crumble_SoftNew",
      "voice": "S802V-639"
    },
    {
      "id": 17,
      "characterlist": "어린홍루 : 5",
      "feeling": "sad",
      "voice": "S802V-640"
    },
    {
      "id": 18,
      "characterlist": "어린가환 : 8",
      "feeling": "surprise2",
      "soundeffect": "SFX_Jean_Crumble_Light",
      "voice": "S802V-641"
    },
    {
      "id": 19,
      "feeling": "angry",
      "soundeffect": "SFX_Cotton_Crumble_SoftNew",
      "voice": "S802V-642"
    },
    {
      "id": 20,
      "feeling": "sad",
      "voice": "S802V-643"
    },
    {
      "id": 21,
      "feeling": "shock",
      "voice": "S802V-644"
    },
    {
      "id": 22,
      "feeling": "sad2",
      "soundeffect": "SFX_Cloth_Crumble",
      "voice": "S802V-645"
    },
    {
      "id": 23,
      "feeling": "sad",
      "soundeffect": "SFX_Cloth_Rubbed_Move",
      "voice": "S802V-646"
    },
    {
      "id": 24,
      "feeling": "surprise2",
      "voice": "S802V-647"
    },
    {
      "id": 25,
      "feeling": "surprise",
      "soundeffect": "SFX_Cotton_Crumble_SoftNew",
      "voice": "S802V-648"
    },
    {
      "id": 26,
      "feeling": "angry3",
      "emotion": "Angry",
      "effect": "CustomCamShake:[20][4][0.3]",
      "soundeffect": "SFX_Jean_Crumble_Hard",
      "voice": "S802V-649"
    },
    {
      "id": 27,
      "feeling": "shock",
      "emotion": "Sweat",
      "effect": "Shake:standing:strength=5:vibrato=10:randomness=50:standingIndexes=[8]",
      "soundeffect": "SFX_Cotton_Crumble_SoftNew",
      "voice": "S802V-650"
    },
    {
      "id": 28,
      "feeling": "idle",
      "voice": "S802V-651"
    },
    {
      "id": 29,
      "feeling": "smile",
      "soundeffect": "SFX_Jean_Crumble_Light",
      "voice": "S802V-652"
    },
    {
      "id": 30,
      "feeling": "idle3",
      "emotion": "Question",
      "soundeffect": "SFX_Cotton_Crumble_SoftNew",
      "voice": "S802V-653"
    },
    {
      "id": 31,
      "feeling": "idle",
      "emotion": "Question",
      "soundeffect": "SFX_Leather_Crumble_Light",
      "voice": "S802V-654"
    },
    {
      "id": 32,
      "feeling": "shock",
      "effect": "StandingJump:position=8",
      "voice": "S802V-655"
    },
    {
      "id": 33,
      "feeling": "smile",
      "effect": "Shake:standing:strength=8:vibrato=10:randomness=50:standingIndexes=[8]",
      "soundeffect": "SFX_Cotton_Crumble_SoftNew",
      "voice": "S802V-656"
    },
    {
      "id": 34,
      "feeling": "idle",
      "soundeffect": "SFX_Jean_Crumble_Light",
      "voice": "S802V-657"
    },
    {
      "id": 35,
      "feeling": "angry",
      "voice": "S802V-658"
    },
    {
      "id": 36,
      "feeling": "idle",
      "soundeffect": "SFX_Jean_Crumble_Light",
      "voice": "S802V-659"
    },
    {
      "id": 37,
      "characterlist": "과거가환 : 9 : mode=FADE_IN",
      "soundeffect": "SFX_Walk_Stone",
      "voice": "S802V-660"
    },
    {
      "id": 38,
      "voice": "S802V-661"
    },
    {
      "id": 39,
      "feeling": "angry",
      "soundeffect": "SFX_Leather_Crumble_Light",
      "voice": "S802V-662"
    },
    {
      "id": 40,
      "feeling": "idle",
      "voice": "S802V-663"
    },
    {
      "id": 41,
      "feeling": "smile",
      "emotion": "Fun",
      "soundeffect": "SFX_Cotton_Crumble_SoftNew",
      "voice": "S802V-664"
    },
    {
      "id": 42,
      "feeling": "sad",
      "voice": "S802V-665"
    },
    {
      "id": 43,
      "feeling": "sad2",
      "soundeffect": "SFX_Cloth_Crumble",
      "voice": "S802V-666"
    },
    {
      "id": 44,
      "feeling": "idle",
      "soundeffect": "SFX_Jean_Crumble_Light",
      "voice": "S802V-667"
    },
    {
      "id": 45,
      "characterlist": "ALL : -1, 공우진 : 3, 과거가모 : 8",
      "feeling": "idle3",
      "bg": "story_fathoms_lab_b_past",
      "cg": "black:FadeIn:[0~0],black:FadeOut:[0.1~1]",
      "effect": "CameraMoveZoom:mode=on:duration=0:vertical=0.1:zoom=1.15:delay=0,\nCustomCamShake:[5][3][3]",
      "voice": "S802V-668"
    },
    {
      "id": 46,
      "effect": "CustomCamShake:[5][3][3], Shake:standing:strength=2:vibrato=5:randomness=50:standingIndexes=[3]",
      "soundeffect": "SFX_Cloth_Crumble",
      "voice": "S802V-669"
    },
    {
      "id": 47,
      "feeling": "smile",
      "effect": "CameraMoveZoom:mode=on:horizontal=0.1:vertical=0.1:zoom=1.18:delay=0, CustomCamShake:[5][3][3]",
      "soundeffect": "SFX_Cotton_Crumble_SoftNew",
      "voice": "S802V-670"
    },
    {
      "id": 48,
      "characterlist": "공우진 : 3, 과거가모 : 8",
      "effect": "CameraMoveZoom:mode=off:delay=0",
      "voice": "S802V-671"
    },
    {
      "id": 49,
      "characterlist": "ALL:-1,흑수들:5",
      "feeling": "idle",
      "bg": "white",
      "cg": "black:FadeIn:[0~0],black:FadeOut:[0.1~1]",
      "soundeffect": "SFX_Jean_Crumble_Light",
      "voice": "S802V-672"
    },
    {
      "id": 50,
      "voice": "S802V-673"
    },
    {
      "id": 51,
      "soundeffect": "SFX_Walk_Wood_2StepOnly",
      "voice": "S802V-674"
    },
    {
      "id": 52,
      "characterlist": "ALL:-1,공우진 : 3, 과거가모 : 8",
      "feeling": "smile",
      "bg": "story_fathoms_lab_b_past",
      "cg": "white:FadeIn:[0~0.1],white:FadeOut:[0.1~1]",
      "soundeffect": "SFX_Cloth_Crumble",
      "voice": "S802V-675"
    },
    {
      "id": 53,
      "feeling": "idle",
      "soundeffect": "SFX_Walk_Wood_2StepOnly",
      "voice": "S802V-676"
    },
    {
      "id": 54,
      "voice": "S802V-677"
    },
    {
      "id": 55,
      "feeling": "angry4",
      "soundeffect": "SFX_Jean_Crumble_Light",
      "voice": "S802V-678"
    },
    {
      "id": 56,
      "cg": "E708:FadeIn",
      "effect": "CameraMoveZoom:mode=on:duration=0.5:vertical=0.1:zoom=1.2:delay=0",
      "voice": "S802V-679"
    },
    {
      "id": 57,
      "soundeffect": "SFX_Cloth_Crumble",
      "voice": "S802V-680"
    },
    {
      "id": 58,
      "characterlist": "ALL : -1, 공우진 : 3, 과거가모 : 8",
      "feeling": "idle3",
      "cg": "E708:FadeOut",
      "effect": "CameraMoveZoom:mode=off:delay=0",
      "soundeffect": "SFX_Leather_Crumble_Light",
      "voice": "S802V-681"
    },
    {
      "id": 59,
      "voice": "S802V-682"
    },
    {
      "id": 60,
      "soundeffect": "SFX_Cotton_Crumble_SoftNew",
      "voice": "S802V-683"
    },
    {
      "id": 61,
      "voice": "S802V-684"
    },
    {
      "id": 62,
      "soundeffect": "SFX_Cloth_Crumble",
      "voice": "S802V-685"
    },
    {
      "id": 63,
      "soundeffect": "SFX_Jean_Crumble_Light",
      "voice": "S802V-686"
    },
    {
      "id": 64,
      "voice": "S802V-687"
    },
    {
      "id": 65,
      "feeling": "smile",
      "soundeffect": "SFX_Cloth_Crumble",
      "voice": "S802V-688"
    },
    {
      "id": 66,
      "characterlist": "공우진 : -1 : mode=FADE_OUT",
      "voice": "S802V-689"
    },
    {
      "id": 67,
      "characterlist": "과거가모:3:mode=FADE_IN,어린홍루: 6 : mode=FADE_IN",
      "feeling": "smile",
      "effect": "Feeling:어린홍루=idle3",
      "soundeffect": "SFX_Walk_Stone",
      "voice": "S802V-690"
    },
    {
      "id": 68,
      "feeling": "idle3",
      "soundeffect": "SFX_Walk_Iron",
      "voice": "S802V-691"
    },
    {
      "id": 69,
      "feeling": "smile2",
      "bgm": "Mystery_Nervous_Ambience",
      "soundeffect": "SFX_Cotton_Crumble_SoftNew",
      "voice": "S802V-692"
    },
    {
      "id": 70,
      "voice": "S802V-693"
    },
    {
      "id": 71,
      "feeling": "angry2",
      "soundeffect": "SFX_Cloth_Crumble",
      "voice": "S802V-694"
    },
    {
      "id": 72,
      "feeling": "sad2",
      "voice": "S802V-695"
    },
    {
      "id": 73,
      "feeling": "idle",
      "soundeffect": "SFX_Jean_Crumble_Light",
      "voice": "S802V-696"
    },
    {
      "id": 74,
      "feeling": "smile",
      "soundeffect": "SFX_Walk_Stone",
      "voice": "S802V-697"
    },
    {
      "id": 75,
      "characterlist": "ALL:-1, 임대옥 : 5",
      "feeling": "idle3",
      "bg": "story_fathoms_lab_b",
      "cg": "white:FadeIn:[0~0.1], white:FadeOut:[0.1~0.2]",
      "bgm": "Brutality",
      "soundeffect": "SFX_Cotton_Crumble_SoftNew",
      "voice": "S802V-698"
    },
    {
      "id": 76
    },
    {
      "id": 77,
      "feeling": "nervous",
      "voice": "S802V-700"
    },
    {
      "id": 78
    },
    {
      "id": 79,
      "soundeffect": "SFX_Cloth_Crumble",
      "voice": "S802V-702"
    },
    {
      "id": 80,
      "feeling": "idle3",
      "bgm": "Relaxation :70",
      "soundeffect": "SFX_Cotton_Crumble_SoftNew",
      "voice": "S802V-703"
    },
    {
      "id": 81,
      "voice": "S802V-704"
    },
    {
      "id": 82,
      "voice": "S802V-705"
    },
    {
      "id": 83,
      "feeling": "smile",
      "soundeffect": "SFX_Cloth_Crumble",
      "voice": "S802V-706"
    },
    {
      "id": 84,
      "characterlist": "홍루 : 5",
      "feeling": "close",
      "voice": "S802V-707"
    },
    {
      "id": 85,
      "feeling": "smile3",
      "soundeffect": "SFX_Cotton_Crumble_SoftNew",
      "voice": "S802V-708"
    },
    {
      "id": 86
    },
    {
      "id": 87,
      "characterlist": "임대옥 : 8:mode=FADE_IN",
      "effect": "Feeling:임대옥=close2"
    },
    {
      "id": 88,
      "feeling": "angry",
      "soundeffect": "SFX_Walk_Iron_Once",
      "voice": "S802V-711"
    },
    {
      "id": 89,
      "feeling": "idle",
      "voice": "S802V-712"
    },
    {
      "id": 90,
      "soundeffect": "SFX_Cloth_Crumble",
      "voice": "S802V-713"
    },
    {
      "id": 91,
      "feeling": "angry",
      "soundeffect": "SFX_Cotton_Crumble_SoftNew",
      "voice": "S802V-714"
    },
    {
      "id": 92,
      "voice": "S802V-715"
    },
    {
      "id": 93,
      "feeling": "idle2",
      "soundeffect": "SFX_Cloth_Crumble",
      "voice": "S802V-716"
    },
    {
      "id": 94,
      "feeling": "angry",
      "soundeffect": "SFX_Cloth_Rubbed_Move",
      "voice": "S802V-717"
    },
    {
      "id": 95,
      "characterlist": "임대옥 : -1 : mode=FADE_OUT, 단테 : 2",
      "voice": "D_Normal"
    },
    {
      "id": 96
    },
    {
      "id": 97,
      "feeling": "surprise",
      "soundeffect": "SFX_Cotton_Crumble_SoftNew",
      "voice": "S802V-720"
    },
    {
      "id": 98,
      "feeling": "close",
      "voice": "S802V-721"
    },
    {
      "id": 99,
      "feeling": "idle",
      "soundeffect": "SFX_Cloth_Crumble",
      "voice": "S802V-722"
    },
    {
      "id": 100,
      "feeling": "smile3",
      "voice": "S802V-723"
    },
    {
      "id": 101,
      "feeling": "idle",
      "soundeffect": "SFX_Walk_Iron_Once",
      "voice": "S802V-724"
    },
    {
      "id": 102,
      "voice": "D_Tok"
    },
    {
      "id": 103,
      "characterlist": "ALL:-1,이상 : 7",
      "feeling": "idle3",
      "voice": "S802V-726"
    },
    {
      "id": 104,
      "feeling": "angry",
      "soundeffect": "SFX_Cloth_Crumble",
      "voice": "S802V-727"
    },
    {
      "id": 105,
      "characterlist": "뫼르소 : 2",
      "soundeffect": "SFX_ClothNCoin_Crumble",
      "voice": "S802V-728"
    },
    {
      "id": 106,
      "characterlist": "이스마엘 : 5",
      "soundeffect": "SFX_Jean_Crumble_Light",
      "voice": "S802V-729"
    },
    {
      "id": 107,
      "characterlist": "싱클레어 : 9",
      "feeling": "sad3",
      "voice": "S802V-730"
    },
    {
      "id": 108,
      "characterlist": "ALL : -1, 임대옥 : 5",
      "soundeffect": "SFX_Jean_Crumble_Light",
      "voice": "S802V-731"
    },
    {
      "id": 109,
      "feeling": "idle3",
      "voice": "S802V-732"
    },
    {
      "id": 110,
      "soundeffect": "SFX_Cloth_Crumble",
      "voice": "S802V-733"
    },
    {
      "id": 111,
      "feeling": "close2",
      "voice": "S802V-734"
    },
    {
      "id": 112,
      "feeling": "idle",
      "soundeffect": "SFX_Walk_Wood_2StepOnly",
      "voice": "S802V-735"
    },
    {
      "id": 113,
      "voice": "S802V-736"
    },
    {
      "id": 114,
      "feeling": "idle3",
      "voice": "S802V-737"
    },
    {
      "id": 115,
      "feeling": "idle",
      "soundeffect": "SFX_Cotton_Crumble_SoftNew",
      "voice": "S802V-738"
    },
    {
      "id": 116,
      "feeling": "close2",
      "soundeffect": "SFX_Cloth_Crumble",
      "voice": "S802V-739"
    },
    {
      "id": 117,
      "feeling": "sad2",
      "voice": "S802V-740"
    },
    {
      "id": 118,
      "characterlist": "그레고르 : 5 : mode =FADE_IN_AFTER_FORMER_FADE_OUT",
      "feeling": "serious",
      "soundeffect": "SFX_Sweat_Crumble_Light",
      "voice": "S802V-741"
    },
    {
      "id": 119
    },
    {
      "id": 120,
      "characterlist": "그레고르 :-1 : mode=FADE_OUT",
      "cg": "black:FadeIn",
      "soundeffect": "SFX_Walk_Wood, SFX_Walk_Iron:delay=0.2, SFX_Walk_Stone:delay=0.3"
    }
  ]
}