{
  "dataList": [
    {
      "id": 0,
      "bg": "story_B1_corridor_D",
      "cg": "black",
      "effect": "CustomCamShake:[8][7][1]",
      "bgm": "Prove_Your_Brutality",
      "soundeffect": "MicNoise",
      "voice": "S802V-1538"
    },
    {
      "id": 1,
      "voice": "S802V-1539"
    },
    {
      "id": 2,
      "voice": "S802V-1540"
    },
    {
      "id": 3,
      "soundeffect": "SFX_Noise2",
      "voice": "S802V-1541"
    },
    {
      "id": 4,
      "characterlist": "사씨사병1:3,사씨사병2:7",
      "cg": "black:FadeOut",
      "effect": "CustomCamShake:[30][13][0.4]",
      "soundeffect": "SFX_Jean_Crumble_Hard",
      "voice": "S802V-1542"
    },
    {
      "id": 5,
      "effect": "CustomCamShake:[10][5][1]",
      "voice": "S802V-1543"
    },
    {
      "id": 6,
      "effect": "CustomCamShake:[50][3][0.3]",
      "soundeffect": "SFX_Run_For_Attack",
      "voice": "S802V-1544"
    }
  ]
}