{
  "dataList": [
    {
      "id": 0,
      "characterlist": "단테:5",
      "emotion": "Question",
      "bg": "story_collapsed corridor",
      "bgm": "They_Were_Here",
      "voice": "D_Normal"
    },
    {
      "id": 1,
      "characterlist": "그레고르:2",
      "feeling": "serious",
      "emotion": "Serious",
      "soundeffect": "SFX_Flesh_Scratch",
      "voice": "S902V-395"
    },
    {
      "id": 2,
      "feeling": "smile",
      "voice": "S902V-396"
    },
    {
      "id": 3,
      "characterlist": "이상:8",
      "feeling": "idle3",
      "soundeffect": "SFX_Cotton_Crumble_SoftNew",
      "voice": "S902V-397"
    },
    {
      "id": 4,
      "characterlist": "ALL:-1,검지제자2:5",
      "feeling": "idle",
      "emotion": "Exclame",
      "voice": "S902V-398"
    },
    {
      "id": 5,
      "feeling": "smile",
      "emotion": "Fun",
      "soundeffect": "SFX_Jean_Crumble_Light",
      "voice": "S902V-399"
    },
    {
      "id": 6,
      "characterlist": "이상:8",
      "feeling": "shock3",
      "soundeffect": "SFX_Cloth_Crumble",
      "voice": "S902V-400"
    },
    {
      "id": 7,
      "feeling": "right",
      "soundeffect": "SFX_Walk_Iron_Once",
      "voice": "S902V-401"
    },
    {
      "id": 8,
      "characterlist": "ALL:-1,이상:8",
      "feeling": "angry",
      "effect": "Transition:type=black:startDuration=0.3:endDuration=0.3:direction=down",
      "soundeffect": "SFX_Cotton_Crumble_SoftNew,SFX_Scene_Change_Whoosh",
      "voice": "S902V-402"
    },
    {
      "id": 9,
      "characterlist": "료슈:3:mode=FADE_IN",
      "feeling": "idle",
      "soundeffect": "SFX_Walk_Iron_Once",
      "voice": "S902V-403"
    },
    {
      "id": 10,
      "characterlist": "ALL:-1,그레고르:2:mode=FADE_IN,검지제자2:5,이상:8",
      "feeling": "smile2",
      "effect": "Transition:type=black:startDuration=0.1:endDuration=0.3:direction=left,Feeling:이상=angry:검지제자2=right",
      "soundeffect": "SFX_Leather_Crumble_Light,SFX_Scene_Change_Whoosh_Slow",
      "voice": "S902V-405"
    },
    {
      "id": 11,
      "feeling": "surprise",
      "voice": "S902V-406"
    },
    {
      "id": 12,
      "characterlist": "라비:7",
      "feeling": "surprise",
      "emotion": "Question",
      "effect": "BloodDust:IN:Standing{7},",
      "soundeffect": "SFX_Sweat_Crumble_Light",
      "voice": "S902V-407"
    },
    {
      "id": 13,
      "characterlist": "료슈:9:mode=FADE_IN:duration=0.3",
      "effect": "CustomCamShake:[15][9][0.5]",
      "soundeffect": "SFX_Walk_Wood_2StepOnly",
      "voice": "S902V-408"
    },
    {
      "id": 14,
      "voice": "S902V-409"
    },
    {
      "id": 15,
      "feeling": "idle3",
      "soundeffect": "SFX_Jean_Crumble_Light",
      "voice": "S902V-410"
    },
    {
      "id": 16,
      "characterlist": "라비:7:mode=FADE_OUT:duration=1.5",
      "feeling": "sad",
      "soundeffect": "SFX_Walk_Iron_Once",
      "voice": "S902V-411"
    },
    {
      "id": 17,
      "characterlist": "ALL:-1,단테:5",
      "emotion": "Question",
      "effect": "BloodDust:OUT:Standing{7},Transition:type=black:startDuration=0.3:endDuration=0.3:direction=down",
      "voice": "D_Tick"
    },
    {
      "id": 18
    },
    {
      "id": 19
    },
    {
      "id": 20,
      "characterlist": "ALL:-1,그레고르:2:mode=FADE_IN,이상:8:mode=FADE_IN, 검지제자2:5",
      "effect": "Transition:type=black:startDuration=0.3:endDuration=0.3:direction=right,Feeling:그레고르=smile2:이상=angry:검지제자2=surprise",
      "soundeffect": "SFX_Walk_Iron_Once,SFX_Scene_Change_Whoosh_Slow"
    },
    {
      "id": 21,
      "feeling": "smile",
      "soundeffect": "SFX_Jean_Crumble_Light",
      "voice": "S902V-416"
    },
    {
      "id": 22,
      "characterlist": "검지제자2:5",
      "feeling": "smile",
      "emotion": "Flower",
      "soundeffect": "SFX_Leather_Crumble_Hard",
      "voice": "S902V-417"
    },
    {
      "id": 23,
      "characterlist": "라비:9:mode=FADE_IN",
      "feeling": "smile",
      "effect": "BloodDust:IN:Standing{9},",
      "soundeffect": "SFX_Cloth_Crumble",
      "voice": "S902V-418"
    },
    {
      "id": 24,
      "feeling": "shock",
      "effect": "Shake:standing:strength=7:vibrato=10:randomness=50:standingIndexes=[8]",
      "soundeffect": "SFX_Walk_Iron_Once",
      "voice": "S902V-419"
    },
    {
      "id": 25,
      "feeling": "smile2",
      "effect": "StandingMove:who=8:to=15:duration=3:ease=OutSine:who=9:to=16:duration=3:ease=OutSine:delay=0.1,CustomCamShake:[15][10][1]",
      "soundeffect": "SFX_Cloth_Rubbed_Move, SFX_Yisang_Walk",
      "voice": "S902V-420"
    },
    {
      "id": 26,
      "characterlist": "ALL:-1,단테:3,이상:5,라비:9",
      "emotion": "Sweat",
      "effect": "Transition:type=black:startDuration=0.3:endDuration=0.3:direction=right",
      "soundeffect": "SFX_Scene_Change_Whoosh",
      "voice": "D_Tok"
    },
    {
      "id": 27,
      "feeling": "surprise",
      "emotion": "Question",
      "soundeffect": "SFX_Cotton_Crumble_SoftNew",
      "voice": "S902V-422"
    },
    {
      "id": 28,
      "characterlist": "이상:5",
      "feeling": "smile2",
      "soundeffect": "SFX_Cloth_Crumble",
      "voice": "S902V-423"
    },
    {
      "id": 29
    },
    {
      "id": 30,
      "characterlist": "ALL:-1,검지제자2:5,그레고르:2",
      "effect": "Shake:standing:strength=4:vibrato=10:randomness=50:standingIndexes=[5],Transition:type=black:startDuration=0.3:endDuration=0.3:direction=left,Feeling:그레고르=smile",
      "soundeffect": "SFX_Walk_Iron_Once",
      "voice": "S902V-425"
    },
    {
      "id": 31,
      "soundeffect": "SFX_Cotton_Crumble_SoftNew",
      "voice": "S902V-426"
    },
    {
      "id": 32,
      "characterlist": "그레고르:2",
      "feeling": "shork",
      "voice": "S902V-427"
    },
    {
      "id": 33,
      "characterlist": "단테:8",
      "voice": "D_Tick"
    },
    {
      "id": 34
    },
    {
      "id": 35,
      "characterlist": "검지제자2:5",
      "feeling": "right",
      "voice": "S902V-431"
    },
    {
      "id": 36,
      "characterlist": "료슈:2",
      "soundeffect": "SFX_Cloth_Crumble",
      "voice": "S902V-432"
    },
    {
      "id": 37,
      "voice": "D_Click"
    },
    {
      "id": 38,
      "feeling": "smile",
      "soundeffect": "SFX_Cotton_Crumble_SoftNew",
      "voice": "S902V-434"
    },
    {
      "id": 39,
      "effect": "BloodDust:OUT:Standing{9},"
    },
    {
      "id": 40,
      "characterlist": "이상:9:mode=FADE_IN",
      "feeling": "close",
      "soundeffect": "SFX_Cloth_Crumble",
      "voice": "S902V-436"
    },
    {
      "id": 41,
      "voice": "S902V-437"
    },
    {
      "id": 42,
      "soundeffect": "SFX_Jean_Crumble_Light",
      "voice": "S902V-438"
    },
    {
      "id": 43,
      "feeling": "smile2",
      "soundeffect": "SFX_Leather_Crumble_Light",
      "voice": "S902V-439"
    },
    {
      "id": 44,
      "characterlist": "ALL:-1,단테:5",
      "emotion": "Sweat",
      "voice": "D_FastTickTok"
    },
    {
      "id": 45,
      "characterlist": "그레고르:2",
      "feeling": "smile",
      "soundeffect": "SFX_Walk_Wood_2StepOnly",
      "voice": "S902V-441"
    },
    {
      "id": 46,
      "characterlist": "검지제자2:8",
      "feeling": "surprise",
      "soundeffect": "SFX_Jean_Crumble_Light",
      "voice": "S902V-442"
    },
    {
      "id": 47,
      "characterlist": "ALL:-1,이상:3,료슈:8",
      "soundeffect": "SFX_Cloth_Crumble",
      "voice": "S902V-443"
    },
    {
      "id": 48,
      "voice": "S902V-444"
    },
    {
      "id": 49,
      "soundeffect": "SFX_Cotton_Crumble_SoftNew",
      "voice": "S902V-445"
    },
    {
      "id": 50,
      "feeling": "idle3",
      "voice": "S902V-446"
    },
    {
      "id": 51,
      "feeling": "sad",
      "soundeffect": "SFX_Cloth_Crumble",
      "voice": "S902V-447"
    },
    {
      "id": 52,
      "feeling": "sad2",
      "voice": "S902V-448"
    },
    {
      "id": 53,
      "feeling": "sad3",
      "voice": "S902V-449"
    },
    {
      "id": 54,
      "feeling": "smile3",
      "soundeffect": "SFX_Walk_Iron_Once",
      "voice": "S902V-450"
    },
    {
      "id": 55,
      "feeling": "close",
      "soundeffect": "SFX_Jean_Crumble_Light",
      "voice": "S902V-451"
    },
    {
      "id": 56,
      "characterlist": "그레고르:5",
      "feeling": "smile",
      "soundeffect": "SFX_Walk_Wood_2StepOnly",
      "voice": "S902V-452"
    },
    {
      "id": 57
    },
    {
      "id": 58
    },
    {
      "id": 59,
      "characterlist": "ALL:-1,료슈:5",
      "soundeffect": "SFX_Cloth_Crumble",
      "voice": "S902V-455"
    },
    {
      "id": 60,
      "feeling": "idle3",
      "voice": "S902V-456"
    },
    {
      "id": 61,
      "feeling": "idle",
      "voice": "S902V-457"
    },
    {
      "id": 62,
      "feeling": "idle2",
      "soundeffect": "SFX_Walk_Iron_Once",
      "voice": "S902V-458"
    },
    {
      "id": 63,
      "feeling": "close",
      "bgm": "They_Were_Here:70",
      "voice": "S902V-459"
    },
    {
      "id": 64,
      "cg": "black:FadeIn",
      "bgm": "They_Were_Here:30",
      "soundeffect": "SFX_Cloth_Crumble",
      "voice": "S902V-460"
    },
    {
      "id": 65,
      "cg": "S919:FadeIn",
      "effect": "CustomCamShake:[5][5][5]",
      "bgm": "And_Day_Passes",
      "voice": "S902V-461"
    },
    {
      "id": 66,
      "effect": "CustomCamShake:[5][5][5]",
      "soundeffect": "SFX_Cigarette_Fire",
      "voice": "S902V-462"
    },
    {
      "id": 67,
      "effect": "CustomCamShake:[5][5][5]",
      "voice": "S902V-463"
    },
    {
      "id": 68,
      "effect": "CustomCamShake:[3][5][5]",
      "soundeffect": "SFX_Cotton_Crumble_SoftNew",
      "voice": "S902V-464"
    },
    {
      "id": 69,
      "effect": "CustomCamShake:[5][5][5]",
      "voice": "S902V-465"
    },
    {
      "id": 70,
      "voice": "S902V-466"
    },
    {
      "id": 71,
      "effect": "CustomCamShake:[5][5][5]",
      "soundeffect": "SFX_Zippo_Open",
      "voice": "S902V-467"
    },
    {
      "id": 72,
      "soundeffect": "SFX_Cigarette_Fire",
      "voice": "S902V-468"
    },
    {
      "id": 73,
      "effect": "CustomCamShake:[3][5][5]",
      "soundeffect": "SFX_Walk_Wood_2StepOnly",
      "voice": "S902V-469"
    },
    {
      "id": 74,
      "voice": "S902V-470"
    },
    {
      "id": 75,
      "effect": "CustomCamShake:[3][5][5]",
      "soundeffect": "SFX_Cloth_Rubbed_Move",
      "voice": "S902V-471"
    },
    {
      "id": 76,
      "soundeffect": "SFX_Cloth_Crumble",
      "voice": "S902V-472"
    },
    {
      "id": 77,
      "voice": "S902V-473"
    },
    {
      "id": 78,
      "effect": "CustomCamShake:[3][5][5]",
      "soundeffect": "SFX_Jean_Crumble_Light",
      "voice": "S902V-474"
    },
    {
      "id": 79,
      "voice": "S902V-475"
    },
    {
      "id": 80,
      "soundeffect": "SFX_Cotton_Crumble_SoftNew",
      "voice": "S902V-476"
    },
    {
      "id": 81,
      "effect": "CustomCamShake:[3][5][5]",
      "voice": "S902V-477"
    },
    {
      "id": 82,
      "soundeffect": "SFX_Cloth_Rubbed_Move",
      "voice": "S902V-478"
    },
    {
      "id": 83,
      "effect": "CustomCamShake:[3][5][5]",
      "voice": "S902V-479"
    },
    {
      "id": 84,
      "soundeffect": "SFX_Cotton_Crumble_SoftNew",
      "voice": "S902V-480"
    },
    {
      "id": 85,
      "soundeffect": "SFX_Cloth_Crumble",
      "voice": "S902V-481"
    },
    {
      "id": 86,
      "voice": "S902V-482"
    },
    {
      "id": 87,
      "cg": "S919:FadeOut",
      "soundeffect": "SFX_Cigarette_fire",
      "voice": "S902V-483"
    },
    {
      "id": 88,
      "characterlist": "ALL:-1,단테:5",
      "cg": "ALL:FadeOut",
      "bgm": "They_Were_Here",
      "voice": "D_Tick"
    },
    {
      "id": 89,
      "voice": "D_Normal"
    },
    {
      "id": 90,
      "characterlist": "료슈:5",
      "feeling": "close",
      "effect": "Transition:type=black:startDuration=0.3:endDuration=0.3:direction=right",
      "soundeffect": "SFX_Cloth_Crumble,SFX_Scene_Change_Whoosh_Slow",
      "voice": "S902V-486"
    },
    {
      "id": 91,
      "feeling": "idle2",
      "voice": "S902V-487"
    },
    {
      "id": 92,
      "characterlist": "단테:5",
      "emotion": "Question",
      "effect": "Transition:type=black:startDuration=0.3:endDuration=0.3:direction=left",
      "voice": "D_Click"
    },
    {
      "id": 93,
      "characterlist": "료슈:5",
      "feeling": "close",
      "effect": "Transition:type=black:startDuration=0.3:endDuration=0.3:direction=right",
      "soundeffect": "SFX_Walk_Iron_Once",
      "voice": "S902V-489"
    },
    {
      "id": 94,
      "feeling": "idle",
      "voice": "S902V-490"
    },
    {
      "id": 95,
      "soundeffect": "SFX_Jean_Crumble_Light",
      "voice": "S902V-491"
    },
    {
      "id": 96,
      "characterlist": "단테:5",
      "effect": "Transition:type=black:startDuration=0.3:endDuration=0.3:direction=left",
      "soundeffect": "SFX_Scene_Change_Whoosh",
      "voice": "D_Normal"
    }
  ]
}