{
  "dataList": [
    {
      "id": 0,
      "characterlist": "검지아비:5",
      "feeling": "idleM",
      "bg": "story_house_spiders_rooftop_embers",
      "bgm": "Call_New_Index:70",
      "soundeffect": "SFX_San_Walk_2",
      "voice": "S903V-2051"
    },
    {
      "id": 1,
      "feeling": "smile3M",
      "voice": "S903V-2052"
    },
    {
      "id": 2,
      "feeling": "smile2M",
      "soundeffect": "SFX_Cotton_Crumble_SoftNew",
      "voice": "S903V-2053"
    },
    {
      "id": 3,
      "characterlist": "료슈9장이후노담배:5:mode=FADE_IN",
      "effect": "BloodDust:IN:Standing{5}",
      "soundeffect": "SFX_Yisang_Walk",
      "voice": "S903V-2054"
    },
    {
      "id": 4
    },
    {
      "id": 5
    },
    {
      "id": 6,
      "characterlist": "검지아비:5",
      "feeling": "idleM",
      "effect": "BloodDust:OUT:Standing{5}",
      "soundeffect": "SFX_Jean_Crumble_Light",
      "voice": "S903V-2057"
    },
    {
      "id": 7,
      "voice": "S903V-2058"
    },
    {
      "id": 8,
      "voice": "S903V-2059"
    },
    {
      "id": 9,
      "feeling": "smileM",
      "voice": "S903V-2060"
    },
    {
      "id": 10,
      "feeling": "idle2M",
      "soundeffect": "SFX_Cloth_Crumble",
      "voice": "S903V-2061"
    },
    {
      "id": 11,
      "characterlist": "료슈9장이후노담배:5",
      "effect": "BloodDust:IN:Standing{5}",
      "voice": "S903V-2062"
    },
    {
      "id": 12,
      "feeling": "close",
      "soundeffect": "SFX_Stretch_HardGrab",
      "voice": "S903V-2063"
    },
    {
      "id": 13,
      "characterlist": "단테:5",
      "effect": "BloodDust:OUT:Standing{5},CustomCamShake:[35][7][0.3]",
      "voice": "D_Tick"
    },
    {
      "id": 14,
      "voice": "D_Normal"
    },
    {
      "id": 15,
      "characterlist": "료슈9장이후노담배:5:mode=FADE_IN_AFTER_FORMER_FADE_OUT",
      "effect": "BloodDust:IN:Standing{5}"
    },
    {
      "id": 16
    },
    {
      "id": 17,
      "soundeffect": "SFX_Metal_Clank"
    },
    {
      "id": 18,
      "bg": "story_house_spiders_rooftop_ashes:mode=FADE_IN:duration=2",
      "voice": "S903V-2069"
    },
    {
      "id": 19,
      "soundeffect": "SFX_Cloth_Crumble",
      "voice": "S903V-2070"
    },
    {
      "id": 20,
      "characterlist": "검지아비:5",
      "feeling": "idleM",
      "effect": "BloodDust:OUT:Standing{5}",
      "voice": "S903V-2071"
    },
    {
      "id": 21,
      "characterlist": "ALL:-1,료슈9장이후노담배:2,검지아비:7",
      "effect": "Feeling:검지아비=idleM,BloodDust:IN:Standing{2}",
      "voice": "S903V-2072"
    },
    {
      "id": 22,
      "feeling": "close",
      "soundeffect": "SFX_Walk_Iron_Once",
      "voice": "S903V-2073"
    },
    {
      "id": 23,
      "feeling": "smileM",
      "voice": "S903V-2074"
    },
    {
      "id": 24,
      "soundeffect": "SFX_Cloth_Crumble",
      "voice": "S903V-2075"
    },
    {
      "id": 25,
      "feeling": "angry",
      "voice": "S903V-2076"
    },
    {
      "id": 26,
      "feeling": "smile2M",
      "voice": "S903V-2077"
    },
    {
      "id": 27,
      "feeling": "smile3M",
      "soundeffect": "SFX_Cotton_Crumble_SoftNew",
      "voice": "S903V-2078"
    },
    {
      "id": 28,
      "feeling": "angry3",
      "voice": "S903V-2079"
    },
    {
      "id": 29,
      "voice": "S903V-2080"
    },
    {
      "id": 30,
      "feeling": "idleM",
      "soundeffect": "SFX_Cloth_Rubbed_Move",
      "voice": "S903V-2081"
    },
    {
      "id": 31,
      "feeling": "happyM",
      "voice": "S903V-2082"
    },
    {
      "id": 32,
      "characterlist": "ALL:-1,검지아비:5",
      "feeling": "smileM",
      "effect": "Transition:type=black:startDuration=0.3:endDuration=0.3:direction=up",
      "soundeffect": "SFX_San_Walk_1,SFX_Scene_Change_Whoosh",
      "voice": "S903V-2083"
    },
    {
      "id": 33,
      "voice": "S903V-2084"
    },
    {
      "id": 34,
      "feeling": "smile2M",
      "soundeffect": "SFX_San_Walk_4",
      "voice": "S903V-2085"
    },
    {
      "id": 35,
      "feeling": "smile3M",
      "voice": "S903V-2086"
    },
    {
      "id": 36,
      "soundeffect": "SFX_Cloth_Crumble",
      "voice": "S903V-2087"
    },
    {
      "id": 37,
      "voice": "S903V-2088"
    },
    {
      "id": 38,
      "feeling": "smile2M",
      "voice": "S903V-2089"
    },
    {
      "id": 39,
      "characterlist": "료슈9장이후노담배:5",
      "feeling": "angry",
      "effect": "Transition:type=black:startDuration=0.3:endDuration=0.3:direction=right,BloodDust:IN:Standing{5}",
      "soundeffect": "SFX_Jean_Crumble_Light,SFX_Scene_Change_Whoosh",
      "voice": "S903V-2090"
    },
    {
      "id": 40,
      "characterlist": "검지아비:5",
      "feeling": "idleM",
      "effect": "Transition:type=black:startDuration=0.3:endDuration=0.3:direction=left,BloodDust:OUT:Standing{5}",
      "soundeffect": "SFX_Scene_Change_Whoosh_Slow",
      "voice": "S903V-2091"
    },
    {
      "id": 41,
      "voice": "S903V-2092"
    },
    {
      "id": 42,
      "soundeffect": "SFX_Cloth_Crumble",
      "voice": "S903V-2093"
    },
    {
      "id": 43,
      "feeling": "smile3M",
      "voice": "S903V-2094"
    },
    {
      "id": 44,
      "feeling": "smile2M",
      "soundeffect": "SFX_Cotton_Crumble_SoftNew",
      "voice": "S903V-2095"
    },
    {
      "id": 45,
      "voice": "S903V-2096"
    },
    {
      "id": 46,
      "voice": "S903V-2097"
    },
    {
      "id": 47,
      "feeling": "smileM",
      "soundeffect": "SFX_San_Walk_2",
      "voice": "S903V-2098"
    },
    {
      "id": 48,
      "voice": "S903V-2099"
    },
    {
      "id": 49,
      "feeling": "idleM",
      "voice": "S903V-2100"
    },
    {
      "id": 50,
      "feeling": "smile3M",
      "soundeffect": "SFX_Cloth_Crumble",
      "voice": "S903V-2101"
    },
    {
      "id": 51,
      "feeling": "idle2M",
      "voice": "S903V-2102"
    }
  ]
}